kbhtcprivateapi/__init__.py
kbhtcprivateapi/api_client.py
kbhtcprivateapi/configuration.py
kbhtcprivateapi/exceptions.py
kbhtcprivateapi/model_utils.py
kbhtcprivateapi/rest.py
kbhtcprivateapi/api/__init__.py
kbhtcprivateapi/api/default_api.py
kbhtcprivateapi/apis/__init__.py
kbhtcprivateapi/model/__init__.py
kbhtcprivateapi/model/get_metadata_response.py
kbhtcprivateapi/model/get_response.py
kbhtcprivateapi/model/post_submit_response.py
kbhtcprivateapi/models/__init__.py
privateapi/__init__.py
privateapi/api_client.py
privateapi/configuration.py
privateapi/exceptions.py
privateapi/model_utils.py
privateapi/rest.py
privateapi/api/__init__.py
privateapi/api/default_api.py
privateapi/apis/__init__.py
privateapi/model/__init__.py
privateapi/model/get_metadata_response.py
privateapi/model/get_response.py
privateapi/model/post_submit_response.py
privateapi/models/__init__.py
kbhtcprivateapi-1.0.0.dist-info/METADATA
kbhtcprivateapi-1.0.0.dist-info/WHEEL
kbhtcprivateapi-1.0.0.dist-info/top_level.txt
kbhtcprivateapi-1.0.0.dist-info/RECORD
