Metadata-Version: 2.1
Name: kbhtcprivateapi
Version: 1.0.0
Summary: Private APi for the HTC grid
Home-page: 
Author: OpenAPI Generator community
Author-email: team@openapitools.org
Keywords: OpenAPI,OpenAPI-Generator,Private APi for the HTC grid
Requires-Python: >=3.6
Requires-Dist: urllib3 >=1.25.3
Requires-Dist: python-dateutil
